ORCSchlange/__init__.py
ORCSchlange/__main__.py
ORCSchlange/bib/__init__.py
ORCSchlange/command/__init__.py
ORCSchlange/command/db.py
ORCSchlange/command/fetch.py
ORCSchlange/command/jquery-3.2.1.min.js
ORCSchlange/config/__init__.py
ORCSchlange/orcid/__init__.py
ORCSchlange/sql/__init__.py
ORCSchlange-0.7.1.dist-info/DESCRIPTION.rst
ORCSchlange-0.7.1.dist-info/METADATA
ORCSchlange-0.7.1.dist-info/RECORD
ORCSchlange-0.7.1.dist-info/WHEEL
ORCSchlange-0.7.1.dist-info/entry_points.txt
ORCSchlange-0.7.1.dist-info/metadata.json
ORCSchlange-0.7.1.dist-info/top_level.txt
