Metadata-Version: 2.0
Name: ORCSchlange
Version: 0.7.1
Summary: Create a nice static publishing websites from ORCIDs.
Home-page: https://github.com/ScaDS/ORC-Schlange
Author: Fabian Gärtner
Author-email: fabian@bioinf.uni-leipzig.de
License: Apache 2.0
Keywords: ORCID Website Bibliography Publication ScaDS
Platform: UNKNOWN
Classifier: Development Status :: 4 - Beta
Classifier: Environment :: Console
Classifier: License :: OSI Approved :: Apache Software License
Classifier: Natural Language :: English
Classifier: Operating System :: OS Independent
Classifier: Programming Language :: Python :: 3
Classifier: Programming Language :: Python :: 3.6
Requires-Dist: pybtex (>=0.21)
Requires-Dist: requests (>=2.18.1)
